README.txt
setup.cfg
setup.py
docs/HISTORY.txt
docs/INSTALL.txt
docs/LICENSE.GPL
docs/LICENSE.txt
easyshop/__init__.py
easyshop.customers.egg-info/PKG-INFO
easyshop.customers.egg-info/SOURCES.txt
easyshop.customers.egg-info/dependency_links.txt
easyshop.customers.egg-info/entry_points.txt
easyshop.customers.egg-info/namespace_packages.txt
easyshop.customers.egg-info/not-zip-safe
easyshop.customers.egg-info/requires.txt
easyshop.customers.egg-info/top_level.txt
easyshop/customers/__init__.py
easyshop/customers/configure.zcml
easyshop/customers/profiles.zcml
easyshop/customers/tests.py
easyshop/customers/adapters/__init__.py
easyshop/customers/adapters/address_management.py
easyshop/customers/adapters/completeness.py
easyshop/customers/adapters/configure.zcml
easyshop/customers/adapters/copy_management.py
easyshop/customers/adapters/customer_management.py
easyshop/customers/browser/__init__.py
easyshop/customers/browser/address_forms.py
easyshop/customers/browser/configure.zcml
easyshop/customers/browser/customer_forms.py
easyshop/customers/browser/customers_container.pt
easyshop/customers/browser/customers_container.py
easyshop/customers/browser/manage_addressbook.pt
easyshop/customers/browser/manage_addressbook.py
easyshop/customers/browser/manage_password.pt
easyshop/customers/browser/manage_payment_methods.pt
easyshop/customers/browser/manage_payment_methods.py
easyshop/customers/browser/my_account.pt
easyshop/customers/content/__init__.py
easyshop/customers/content/address.py
easyshop/customers/content/configure.zcml
easyshop/customers/content/containers.py
easyshop/customers/content/customer.py
easyshop/customers/portlets/__init__.py
easyshop/customers/portlets/configure.zcml
easyshop/customers/portlets/my_account.pt
easyshop/customers/portlets/my_account.py
easyshop/customers/profiles/__init__.py
easyshop/customers/profiles/default/catalog.xml
easyshop/customers/profiles/default/portlets.xml
easyshop/customers/profiles/default/types.xml
easyshop/customers/profiles/default/workflows.xml
easyshop/customers/profiles/default/types/Address.xml
easyshop/customers/profiles/default/types/Customer.xml
easyshop/customers/profiles/default/types/CustomersContainer.xml
easyshop/customers/profiles/default/types/SessionsContainer.xml
